layer_values_monitor/__init__.py
layer_values_monitor/catchup.py
layer_values_monitor/config_watcher.py
layer_values_monitor/constants.py
layer_values_monitor/custom_feeds.py
layer_values_monitor/custom_types.py
layer_values_monitor/discord.py
layer_values_monitor/dispute.py
layer_values_monitor/evm_call.py
layer_values_monitor/logger.py
layer_values_monitor/main.py
layer_values_monitor/monitor.py
layer_values_monitor/saga_contract.py
layer_values_monitor/telliot_feeds.py
layer_values_monitor/threshold_config.py
layer_values_monitor/trb_bridge.py
layer_values_monitor/utils.py
layer_values_monitor-0.1.5.dist-info/METADATA
layer_values_monitor-0.1.5.dist-info/WHEEL
layer_values_monitor-0.1.5.dist-info/entry_points.txt
layer_values_monitor-0.1.5.dist-info/RECORD
