Metadata-Version: 2.4
Name: layer-values-monitor
Version: 0.1.5
Summary: Layer values monitor
Author: Tellor Development Community
License-Expression: MIT
Requires-Python: >=3.12
Requires-Dist: aiohttp>=3.8.0
Requires-Dist: discordwebhook>=1.0.3
Requires-Dist: eth-abi==5.2.0
Requires-Dist: pandas>=2.2.3
Requires-Dist: python-dotenv>=1.0.1
Requires-Dist: telliot-feeds>=0.2.2
Requires-Dist: websockets==13.1
